gerber_writer/__init__.py
gerber_writer/lutils.py
gerber_writer/macros.py
gerber_writer/padmasters.py
gerber_writer/writer.py
gerber_writer/writer_test.py
gerber_writer-0.4.3.2.dist-info/LICENSE
gerber_writer-0.4.3.2.dist-info/METADATA
gerber_writer-0.4.3.2.dist-info/WHEEL
gerber_writer-0.4.3.2.dist-info/top_level.txt
gerber_writer-0.4.3.2.dist-info/RECORD
