Metadata-Version: 2.1
Name: gerber_writer
Version: 0.4.3.2
Summary: A library to write Gerber files
Author-email: Karel Tavernier <karel_tavernier@hotmail.com>
License: Apache 2.0 License
Project-URL: Repository, https://github.com/karel-tavernier/gerber_writer
Project-URL: Documentation, https://karel-tavernier.github.io/gerber_writer/html
Keywords: Gerber,RS-274X,PCB,CAD,CAM,library
Classifier: Programming Language :: Python :: 3
Classifier: License :: OSI Approved :: Apache Software License
Classifier: Operating System :: OS Independent
Classifier: Development Status :: 5 - Production/Stable
Classifier: Intended Audience :: Developers
Classifier: Topic :: Scientific/Engineering :: Electronic Design Automation (EDA)
Classifier: Topic :: Software Development :: Libraries
Requires-Python: >=3.9
License-File: LICENSE
